icheck-1.8.dist-info/zip-safe
icheck-1.8.dist-info/METADATA
icheck-1.8.dist-info/DESCRIPTION.rst
icheck-1.8.dist-info/RECORD
icheck-1.8.dist-info/metadata.json
icheck-1.8.dist-info/WHEEL
icheck-1.8.dist-info/top_level.txt
icheck-1.8.dist-info/entry_points.txt
icheck/__init__.py
