Metadata-Version: 2.0
Name: icheck
Version: 1.8
Summary: Syntax checker for python using inotify
Home-page: http://blitz.works/icheck
Author: Da_Blitz
Author-email: code@blitz.works
License: MIT BSD
Download-URL: http://blitz.works/icheck/archive/tip.zip
Keywords: butter syntax check test doctest
Platform: UNKNOWN
Classifier: Development Status :: 5 - Production/Stable
Classifier: Environment :: Console
Classifier: Intended Audience :: Developers
Classifier: License :: OSI Approved :: BSD License
Classifier: Operating System :: POSIX :: Linux
Classifier: Programming Language :: Python :: 3
Classifier: Topic :: Software Development :: Testing
Requires-Dist: butter (>=0.9)
Requires-Dist: blessed (>=1.9.4)
